aiohttp_spyne/__init__.py
aiohttp_spyne/aio_base.py
aiohttp_spyne/aio_method_ctx.py
aiohttp_spyne/aio_spyne.py
aiohttp_spyne/aio_transport_ctx.py
aiohttp_spyne/py.typed
aiohttp_spyne-1.6.0.dist-info/LICENSE
aiohttp_spyne-1.6.0.dist-info/METADATA
aiohttp_spyne-1.6.0.dist-info/WHEEL
aiohttp_spyne-1.6.0.dist-info/RECORD
