Metadata-Version: 2.1
Name: aiohttp-spyne
Version: 1.6.0
Summary: Aiohttp transport for Spyne RPC library
Home-page: https://github.com/katajakasa/aiohttp-spyne
License: LGPL-2.1-only
Keywords: asyncio,aiohttp,spyne,soap
Author: Tuomas Virtanen
Author-email: katajakasa@gmail.com
Requires-Python: >=3.8,<4.0
Classifier: Development Status :: 5 - Production/Stable
Classifier: Framework :: AsyncIO
Classifier: Intended Audience :: Developers
Classifier: License :: OSI Approved
Classifier: Operating System :: OS Independent
Classifier: Programming Language :: Python :: 3
Classifier: Programming Language :: Python :: 3.8
Classifier: Programming Language :: Python :: 3.9
Classifier: Programming Language :: Python :: 3.10
Classifier: Programming Language :: Python :: 3.11
Classifier: Programming Language :: Python :: 3.12
Classifier: Topic :: Internet :: WWW/HTTP
Classifier: Topic :: Internet :: WWW/HTTP :: HTTP Servers
Requires-Dist: aiohttp (>=3.9.0,<4.0.0)
Requires-Dist: spyne (>=2.14.0,<3.0.0)
Project-URL: Repository, https://github.com/katajakasa/aiohttp-spyne
